{
    "photo": {
        "id": "5763589730",
         "secret": "ae7116f625",
         "server": "2291",
         "farm": 3,
         "dateuploaded": "1306458582",
         "isfavorite": 0,
         "license": "1",
         "safety_level": "0",
         "rotation": 0,
         "originalsecret": "663be4f6f8",
         "originalformat": "jpg",
         "owner": {
            "nsid": "14224905@N08",
             "username": "paazio",
             "realname": "",
             "location": "Helsinki, Finland",
             "iconserver": "1350",
             "iconfarm": 2,
             "path_alias": "paazio"
        },
         "title": {
            "_content": "Kyoto 2011-05-02 107th Embu Taikai, Jikishinkageryu Naginatajutsu"
        },
         "description": {
            "_content": "Himeji members"
        },
         "visibility": {
            "ispublic": 1,
             "isfriend": 0,
             "isfamily": 0
        },
         "dates": {
            "posted": "1306458582",
             "taken": "2011-05-02 10:12:33",
             "takengranularity": "0",
             "lastupdate": "1312882567"
        },
         "views": "152",
         "editability": {
            "cancomment": 0,
             "canaddmeta": 0
        },
         "publiceditability": {
            "cancomment": 1,
             "canaddmeta": 0
        },
         "usage": {
            "candownload": 1,
             "canblog": 0,
             "canprint": 0,
             "canshare": 1
        },
         "comments": {
            "_content": "0"
        },
         "notes": {
            "note": [
                
            ]
        },
         "people": {
            "haspeople": 0
        },
         "tags": {
            "tag": [
                {
                    "id": "14132092-5763589730-3110",
                     "author": "14224905@N08",
                     "raw": "kyoto",
                     "_content": "kyoto",
                     "machine_tag": 0
                },
                 {
                    "id": "14132092-5763589730-104364",
                     "author": "14224905@N08",
                     "raw": "taikai",
                     "_content": "taikai",
                     "machine_tag": 0
                },
                 {
                    "id": "14132092-5763589730-32472872",
                     "author": "14224905@N08",
                     "raw": "jikishinkageryu",
                     "_content": "jikishinkageryu",
                     "machine_tag": 0
                },
                 {
                    "id": "14132092-5763589730-117865",
                     "author": "14224905@N08",
                     "raw": "naginata",
                     "_content": "naginata",
                     "machine_tag": 0
                },
                 {
                    "id": "14132092-5763589730-7733183",
                     "author": "14224905@N08",
                     "raw": "japanesemartialart",
                     "_content": "japanesemartialart",
                     "machine_tag": 0
                },
                 {
                    "id": "14132092-5763589730-1762507",
                     "author": "14224905@N08",
                     "raw": "\u8599\u5200",
                     "_content": "\u8599\u5200",
                     "machine_tag": 0
                },
                 {
                    "id": "14132092-5763589730-1762505",
                     "author": "14224905@N08",
                     "raw": "\u306a\u304e\u306a\u305f",
                     "_content": "\u306a\u304e\u306a\u305f",
                     "machine_tag": 0
                },
                 {
                    "id": "14132092-5763589730-4942608",
                     "author": "14224905@N08",
                     "raw": "\u6b66\u9053",
                     "_content": "\u6b66\u9053",
                     "machine_tag": 0
                },
                 {
                    "id": "14132092-5763589730-18964",
                     "author": "14224905@N08",
                     "raw": "\u65e5\u672c",
                     "_content": "\u65e5\u672c",
                     "machine_tag": 0
                },
                 {
                    "id": "14132092-5763589730-19273084",
                     "author": "14224905@N08",
                     "raw": "\u76f4\u5fc3\u5f71\u6d41",
                     "_content": "\u76f4\u5fc3\u5f71\u6d41",
                     "machine_tag": 0
                },
                 {
                    "id": "14132092-5763589730-1038",
                     "author": "14224905@N08",
                     "raw": "japan",
                     "_content": "japan",
                     "machine_tag": 0
                },
                 {
                    "id": "14132092-5763589730-290",
                     "author": "14224905@N08",
                     "raw": "people",
                     "_content": "people",
                     "machine_tag": 0
                },
                 {
                    "id": "14132092-5763589730-357489",
                     "author": "14224905@N08",
                     "raw": "budo",
                     "_content": "budo",
                     "machine_tag": 0
                },
                 {
                    "id": "14132092-5763589730-1970",
                     "author": "14224905@N08",
                     "raw": "japanese",
                     "_content": "japanese",
                     "machine_tag": 0
                },
                 {
                    "id": "14132092-5763589730-4711",
                     "author": "14224905@N08",
                     "raw": "martialart",
                     "_content": "martialart",
                     "machine_tag": 0
                },
                 {
                    "id": "14132092-5763589730-1641557",
                     "author": "14224905@N08",
                     "raw": "\u6b66\u8853",
                     "_content": "\u6b66\u8853",
                     "machine_tag": 0
                },
                 {
                    "id": "14132092-5763589730-6595506",
                     "author": "14224905@N08",
                     "raw": "keikogi",
                     "_content": "keikogi",
                     "machine_tag": 0
                }
            ]
        },
         "location": {
            "latitude": 35.016361,
             "longitude": 135.780869,
             "accuracy": "16",
             "context": "0",
             "locality": {
                "_content": "Kyoto-shi",
                 "place_id": "9cw_d0JQV7obLp8N5A",
                 "woeid": "15015372"
            },
             "region": {
                "_content": "Kyoto Prefecture",
                 "place_id": "vAd3SUZTUb5ktGbw",
                 "woeid": "2345871"
            },
             "country": {
                "_content": "Japan",
                 "place_id": "W3QedCZTUb5Ez.rF.Q",
                 "woeid": "23424856"
            },
             "place_id": "9cw_d0JQV7obLp8N5A",
             "woeid": "15015372"
        },
         "geoperms": {
            "ispublic": 1,
             "iscontact": 0,
             "isfriend": 0,
             "isfamily": 0
        },
         "urls": {
            "url": [
                {
                    "type": "photopage",
                     "_content": "http:\/\/www.flickr.com\/photos\/paazio\/5763589730\/"
                }
            ]
        },
         "media": "photo"
    },
     "stat": "ok"
}